functionsmith/agent.py
functionsmith/code_parser.py
functionsmith/executor.py
functionsmith/llm.py
functionsmith-0.1.4.dist-info/licenses/LICENSE
functionsmith-0.1.4.dist-info/METADATA
functionsmith-0.1.4.dist-info/WHEEL
functionsmith-0.1.4.dist-info/entry_points.txt
functionsmith-0.1.4.dist-info/top_level.txt
functionsmith-0.1.4.dist-info/RECORD
