Metadata-Version: 2.4
Name: functionsmith
Version: 0.1.4
Summary: Functionsmith is a general-purpose problem-solving agent using dynamic function calling
Author-email: Simon Ilyushchenko <simonf@google.com>
License: Apache-2.0
Project-URL: Homepage, https://github.com/google/earthengine-community/tree/master/experimental/functionsmith
Keywords: ai,agent,llm
Classifier: Development Status :: 3 - Alpha
Classifier: Intended Audience :: Developers
Classifier: Intended Audience :: Science/Research
Classifier: License :: OSI Approved :: Apache Software License
Classifier: Operating System :: OS Independent
Classifier: Programming Language :: Python :: 3 :: Only
Classifier: Programming Language :: Python :: 3
Classifier: Programming Language :: Python :: 3.9
Classifier: Programming Language :: Python :: 3.10
Classifier: Programming Language :: Python :: 3.11
Classifier: Programming Language :: Python :: 3.12
Classifier: Programming Language :: Python :: 3.13
Classifier: Programming Language :: Python
Classifier: Topic :: Scientific/Engineering :: Artificial Intelligence
Classifier: Typing :: Typed
Requires-Python: >=3.9
License-File: LICENSE
Requires-Dist: anthropic
Requires-Dist: docstring_parser
Requires-Dist: google-genai
Requires-Dist: openai
Dynamic: license-file
